{"cameraMode":{"drawMode":0,"name":"Shaded","section":"Shading Mode"},"sceneLighting":true,"audioPlay":false,"sceneViewState":{"m_AlwaysRefresh":false,"showFog":true,"showSkybox":true,"showFlares":true,"showImageEffects":true,"showParticleSystems":true,"showVisualEffectGraphs":true,"m_FxEnabled":true},"in2DMode":false,"pivot":{"x":1.7725077867507935,"y":-1.3116520643234254,"z":14.159903526306153},"rotation":{"x":0.22920450568199159,"y":0.1697225719690323,"z":-0.040625765919685367,"w":0.9581409096717835},"size":10.0,"orthographic":false}